tensorflow_quantum/__init__.py
tensorflow_quantum/core/__init__.py
tensorflow_quantum/core/ops/__init__.py
tensorflow_quantum/core/ops/_tfq_adj_grad.so
tensorflow_quantum/core/ops/_tfq_calculate_unitary_op.so
tensorflow_quantum/core/ops/_tfq_ps_utils.so
tensorflow_quantum/core/ops/_tfq_simulate_ops.so
tensorflow_quantum/core/ops/_tfq_utility_ops.so
tensorflow_quantum/core/ops/batch_util.py
tensorflow_quantum/core/ops/circuit_execution_ops.py
tensorflow_quantum/core/ops/cirq_ops.py
tensorflow_quantum/core/ops/load_module.py
tensorflow_quantum/core/ops/tfq_adj_grad_op.py
tensorflow_quantum/core/ops/tfq_ps_util_ops.py
tensorflow_quantum/core/ops/tfq_simulate_ops.py
tensorflow_quantum/core/ops/tfq_unitary_op.py
tensorflow_quantum/core/ops/tfq_utility_ops.py
tensorflow_quantum/core/ops/math_ops/__init__.py
tensorflow_quantum/core/ops/math_ops/_tfq_math_ops.so
tensorflow_quantum/core/ops/math_ops/fidelity_op.py
tensorflow_quantum/core/ops/math_ops/inner_product_op.py
tensorflow_quantum/core/ops/math_ops/simulate_mps.py
tensorflow_quantum/core/ops/noise/__init__.py
tensorflow_quantum/core/ops/noise/_tfq_noise_ops.so
tensorflow_quantum/core/ops/noise/noisy_expectation_op.py
tensorflow_quantum/core/ops/noise/noisy_sampled_expectation_op.py
tensorflow_quantum/core/ops/noise/noisy_samples_op.py
tensorflow_quantum/core/proto/__init__.py
tensorflow_quantum/core/proto/pauli_sum_pb2.py
tensorflow_quantum/core/proto/program_pb2.py
tensorflow_quantum/core/proto/projector_sum_pb2.py
tensorflow_quantum/core/serialize/__init__.py
tensorflow_quantum/core/serialize/op_deserializer.py
tensorflow_quantum/core/serialize/op_serializer.py
tensorflow_quantum/core/serialize/serializable_gate_set.py
tensorflow_quantum/core/serialize/serializer.py
tensorflow_quantum/datasets/__init__.py
tensorflow_quantum/datasets/cluster_state.py
tensorflow_quantum/datasets/spin_system.py
tensorflow_quantum/python/__init__.py
tensorflow_quantum/python/quantum_context.py
tensorflow_quantum-0.7.5.dist-info/METADATA
tensorflow_quantum-0.7.5.dist-info/WHEEL
tensorflow_quantum-0.7.5.dist-info/top_level.txt
tensorflow_quantum-0.7.5.dist-info/RECORD
