Metadata-Version: 2.4
Name: tensorflow-quantum
Version: 0.7.5
Summary: Library for hybrid quantum-classical machine learning.
Home-page: https://github.com/tensorflow/quantum/
Author: The TensorFlow Quantum Authors
Author-email: tensorflow-quantum-team@google.com
License: Apache 2.0
Keywords: tensorflow machine learning quantum qml
Classifier: Development Status :: 3 - Alpha
Classifier: Intended Audience :: Developers
Classifier: Intended Audience :: Education
Classifier: Intended Audience :: Science/Research
Classifier: Programming Language :: Python :: 3
Classifier: Programming Language :: Python :: 3.9
Classifier: Programming Language :: Python :: 3.10
Classifier: Programming Language :: Python :: 3.11
Classifier: Programming Language :: Python :: 3.12
Classifier: Topic :: Scientific/Engineering
Classifier: Topic :: Scientific/Engineering :: Artificial Intelligence
Classifier: Topic :: Scientific/Engineering :: Mathematics
Classifier: Topic :: Scientific/Engineering :: Physics
Classifier: Topic :: Scientific/Engineering :: Quantum Computing
Requires-Python: >=3.9
Requires-Dist: cirq-core==1.3.0
Requires-Dist: cirq-google==1.3.0
Requires-Dist: sympy==1.14
Requires-Dist: tf-keras~=2.16.0
Requires-Dist: contourpy<=1.3.0
Requires-Dist: numpy<2.0
Requires-Dist: scipy<=1.12.0
Requires-Dist: jax<0.4.24
Requires-Dist: jaxlib<0.4.24
Requires-Dist: pillow<=11.0
Requires-Dist: networkx<3.3
Requires-Dist: h5py==3.10.0
Requires-Dist: matplotlib<3.10
Requires-Dist: importlib_metadata<5
Requires-Dist: protobuf==4.25.8
Provides-Extra: and-tensorflow
Requires-Dist: tensorflow<2.17,>=2.16; extra == "and-tensorflow"
Provides-Extra: extras
Requires-Dist: tensorflow<2.17,>=2.16; extra == "extras"
Dynamic: author
Dynamic: author-email
Dynamic: classifier
Dynamic: description
Dynamic: home-page
Dynamic: keywords
Dynamic: license
Dynamic: provides-extra
Dynamic: requires-dist
Dynamic: requires-python
Dynamic: summary
